unsloth_studio/__init__.py
unsloth_studio/chat.py
unsloth_studio/evaluation.py
unsloth_studio/losses.py
unsloth_studio/utils.py
unsloth_studio/tests/__init__.py
unsloth_studio/tests/losses.py
unsloth_studio-2025.3.1.dist-info/LICENSE
unsloth_studio-2025.3.1.dist-info/METADATA
unsloth_studio-2025.3.1.dist-info/WHEEL
unsloth_studio-2025.3.1.dist-info/top_level.txt
unsloth_studio-2025.3.1.dist-info/RECORD
