Metadata-Version: 2.2
Name: unsloth_studio
Version: 2025.3.1
Summary: Unsloth Studio
Author: Unsloth AI team
Author-email: info@unsloth.ai
Maintainer-email: Daniel Han <danielhanchen@gmail.com>, Michael Han <info@unsloth.ai>
License:                     GNU AFFERO GENERAL PUBLIC LICENSE
Project-URL: homepage, http://www.unsloth.ai
Project-URL: documentation, https://github.com/unslothai/unsloth
Project-URL: repository, https://github.com/unslothai/unsloth
Keywords: ai,llm
Classifier: Programming Language :: Python
Requires-Python: <3.13,>=3.9
License-File: LICENSE
Requires-Dist: torch
Requires-Dist: triton; platform_system == "Linux"
Requires-Dist: packaging
Requires-Dist: tyro
Requires-Dist: tqdm
Requires-Dist: psutil
Requires-Dist: wheel>=0.42.0
Requires-Dist: numpy
Requires-Dist: pillow
